mapify/__init__.py
mapify/decrypt.py
mapify/default.toml
mapify/encrypt.py
mapify/functions.py
mapify/generate.py
mapify-1.1.0.dist-info/LICENSE
mapify-1.1.0.dist-info/METADATA
mapify-1.1.0.dist-info/WHEEL
mapify-1.1.0.dist-info/top_level.txt
mapify-1.1.0.dist-info/RECORD
