Metadata-Version: 2.1
Name: mapify
Version: 1.1.0
Summary: Encrypt and decrypt texts on a secure way using maps
Home-page: https://github.com/RubeMeuleman/mapify.git
Author: Jinzo
Author-email: developer.rube@gmail.com
Classifier: Programming Language :: Python :: 3
Classifier: License :: OSI Approved :: MIT License
Classifier: Operating System :: OS Independent
Requires-Python: >=3
License-File: LICENSE
Requires-Dist: toml>=0.10.2
